{
    "example": {
        "POPSCI_columnsDef": {
            "": "|p{1.5cm} | X | p{2.5cm}| p{3.5cm}|"
        },
        "POPSCI_content": {
            "Content": "Major role in the organisation of a popular science workshop."
        },
        "POPSCI_endDate": {
            "End": ""
        },
        "POPSCI_include": {
            "": "true"
        },
        "POPSCI_initiative": {
            "Initiative": "PopSci Project"
        },
        "POPSCI_location": {
            "Location": "London, England"
        },
        "POPSCI_startDate": {
            "Start": "2022-09-15"
        },
        "POPSCI_title": {
            "": "Organisation of workshop"
        }
    }
}