{
    "example1": {
        "PUB_fullText": [
            "",
            "Entry contents"
        ],
        "PUB_include": [
            "",
            "true"
        ],
        "PUB_key": [
            "",
            "mypublications:johnDoe"
        ],
        "PUB_latexEntry": [
            "",
            ""
        ]
    },
    "example2": {
        "PUB_fullText": [
            "",
            "John Doe (Feb. 2023). \u201cThe Joy of Fullstack Developing\u201d"
        ],
        "PUB_include": [
            "",
            "true"
        ],
        "PUB_key": [
            "",
            ""
        ],
        "PUB_latexEntry": [
            "",
            ""
        ]
    }
}